{
  "id": "heap-merge",
  "type": "heap",
  "title": "힙 — 최소 비용 합치기",
  "belt": "스택큐",
  "desc": "매번 가장 작은 둘을 합칠 때 총비용 최소화(백준 1715 원형).",
  "expected_complexity": "O(N log N)",
  "think_prompt": "왜 '항상 가장 작은 두 개'를 먼저 합쳐야 총비용이 최소인가? 그걸 매번 O(log N)에 꺼내주는 자료구조는?",
  "think_model": "일찍 합친 묶음은 이후 합칠 때마다 비용에 반복 포함 → 작은 것부터 합쳐야 반복 비용이 작다. 최소 힙(heapq)이 '현재 최소 2개'를 O(log N)에 제공.",
  "code": "import heapq\n\ndef min_merge_cost(cards):\n    heap = list(cards)\n    heapq.heapify(heap)\n    total = 0\n    while len(heap) > 1:\n        a = heapq.heappop(heap)\n        b = heapq.heappop(heap)\n        total += a + b\n        heapq.heappush(heap, a + b)\n    return total\n",
  "subgoals": [
    {
      "label": "① 리스트를 힙으로 (heapify O(N))",
      "lines": [
        0,
        5
      ]
    },
    {
      "label": "② 최소 2개 pop → 합쳐서 비용 누적 → 다시 push",
      "lines": [
        6,
        10
      ]
    },
    {
      "label": "③ 하나 남으면 총비용 반환",
      "lines": [
        11,
        11
      ]
    }
  ],
  "line_notes": {
    "4": "heapify — 정렬(N log N)보다 싼 O(N) 힙 구성",
    "7": "heappop = 최솟값 O(log N)",
    "10": "★합친 묶음을 다시 넣는다 — 다음 라운드의 후보"
  },
  "func": "min_merge_cost",
  "tests": [
    {
      "args": [
        [
          10,
          20,
          40
        ]
      ],
      "expected": 100
    },
    {
      "args": [
        [
          1,
          2,
          3,
          4
        ]
      ],
      "expected": 19
    },
    {
      "args": [
        [
          7
        ]
      ],
      "expected": 0
    },
    {
      "args": [
        []
      ],
      "expected": 0
    },
    {
      "args": [
        [
          5
        ]
      ],
      "expected": 0
    },
    {
      "args": [
        [
          1,
          1
        ]
      ],
      "expected": 2
    },
    {
      "args": [
        [
          1,
          2,
          3
        ]
      ],
      "expected": 9
    },
    {
      "args": [
        [
          10,
          10,
          10,
          10
        ]
      ],
      "expected": 80
    },
    {
      "args": [
        [
          100,
          1
        ]
      ],
      "expected": 101
    },
    {
      "args": [
        [
          3,
          5,
          7,
          9,
          11
        ]
      ],
      "expected": 78
    },
    {
      "args": [
        [
          1,
          1,
          1,
          1,
          1,
          1,
          1,
          1,
          1,
          1
        ]
      ],
      "expected": 34
    },
    {
      "args": [
        [
          2,
          4
        ]
      ],
      "expected": 6
    },
    {
      "args": [
        [
          9,
          8,
          7,
          6,
          5,
          4,
          3,
          2,
          1
        ]
      ],
      "expected": 135
    },
    {
      "args": [
        [
          1000,
          1000
        ]
      ],
      "expected": 2000
    },
    {
      "args": [
        [
          6,
          6,
          6
        ]
      ],
      "expected": 30
    },
    {
      "args": [
        [
          1,
          2,
          3,
          4,
          5,
          6,
          7,
          8,
          9,
          10,
          11,
          12
        ]
      ],
      "expected": 264
    }
  ],
  "perf": {
    "gen": "def make_args():\n    return ([i % 1000 + 1 for i in range(200000)],)",
    "time_limit": 3.0
  },
  "diagram": {
    "caption": "작은 것부터 합쳐야 '반복 포함되는 비용'이 최소",
    "fps": 1.0,
    "frames": [
      "힙: [10, 20, 40]\n\npop 10, 20 → 합 30 (비용 30)",
      "힙: [30, 40]\n\npop 30, 40 → 합 70 (비용 +70)",
      "힙: [70]\n\n총비용 30+70 = 100 ✅ (큰 걸 먼저 합치면 60+100=160)"
    ]
  },
  "resources": [
    {
      "name": "백준 1715 카드 정렬하기 (골드4 — 원형)",
      "url": "https://www.acmicpc.net/problem/1715"
    },
    {
      "name": "HackerRank — QHEAP1",
      "url": "https://www.hackerrank.com/challenges/qheap1/problem"
    },
    {
      "name": "HackerRank — Jesse and Cookies",
      "url": "https://www.hackerrank.com/challenges/jesse-and-cookies/problem"
    },
    {
      "name": "백준 11279 최대 힙 (실버2)",
      "url": "https://www.acmicpc.net/problem/11279"
    }
  ],
  "statement": "문제 설명\n숫자가 적힌 카드 묶음들이 있습니다. 두 묶음을 합치는 비용은 두 묶음의 크기의 합이며, 합쳐진 묶음은 그 합 크기의 새 묶음이 됩니다. 모든 묶음이 하나가 될 때까지 합칠 때, 비용의 총합이 최소가 되도록 합치는 순서를 정하려 합니다.\n\n각 묶음의 크기 배열 cards가 주어질 때, 최소 총비용을 반환하도록 min_merge_cost 함수를 작성하세요.\n\n제한사항\n- 1 ≤ cards의 길이 ≤ 200,000\n- 1 ≤ cards[i] ≤ 10,000\n- 묶음이 하나뿐이면 비용은 0입니다.\n\n입출력 예\ncards = [10, 20, 40]  →  result = 100\ncards = [1, 2, 3, 4]  →  result = 19\n\n입출력 예 설명\n예제 #1: 10+20=30(비용 30), 30+40=70(비용 70) → 총 100. 40을 먼저 합치면 총비용이 더 커집니다.",
  "statement_lang": "ko"
}