{
  "id": "bfs-grid",
  "type": "bfs",
  "title": "BFS — 격자 최단거리",
  "belt": "탐색",
  "desc": "격자에서 시작→목표 최단거리. 코테 최빈출 유형(삼성 단골).",
  "expected_complexity": "O(N·M)",
  "think_prompt": "BFS가 '최단거리'를 보장하는 이유는? 핵심 자료구조는? (한 줄로 선언 후 Enter — 또는 ✏️ 연필로 격자에 파도가 퍼지는 그림을 먼저 그려보세요)",
  "think_model": "큐(FIFO). 같은 거리의 층을 전부 소진한 뒤 다음 층으로 가므로, 목표에 처음 닿는 순간이 곧 최단거리다.",
  "code": "from collections import deque\n\ndef bfs(grid, start, goal):\n    n, m = len(grid), len(grid[0])\n    q = deque([(start, 0)])\n    seen = {start}\n    while q:\n        (r, c), d = q.popleft()\n        if (r, c) == goal:\n            return d\n        for dr, dc in ((1,0),(-1,0),(0,1),(0,-1)):\n            nr, nc = r + dr, c + dc\n            if 0 <= nr < n and 0 <= nc < m:\n                if grid[nr][nc] == 0 and (nr, nc) not in seen:\n                    seen.add((nr, nc))\n                    q.append(((nr, nc), d + 1))\n    return -1\n",
  "subgoals": [
    {
      "label": "① 준비: 큐에 (시작점, 거리0) 넣고 방문 표시",
      "lines": [
        0,
        5
      ]
    },
    {
      "label": "② 꺼내기: 큐 앞에서 하나 꺼내 목표면 거리 반환",
      "lines": [
        6,
        9
      ]
    },
    {
      "label": "③ 확장: 상하좌우 이웃 중 (범위 안·벽 아님·미방문)만 방문 표시 후 큐에 +1 거리로",
      "lines": [
        10,
        15
      ]
    },
    {
      "label": "④ 실패: 큐가 비면 도달 불가 = -1",
      "lines": [
        16,
        16
      ]
    }
  ],
  "line_notes": {
    "0": "deque — 양끝 O(1) 큐. BFS의 심장",
    "3": "격자 크기: n=행, m=열",
    "4": "큐 원소는 (좌표, 거리) 튜플 — 시작 거리는 0",
    "5": "seen 집합 — 재방문 차단(무한루프 방지). '큐에 넣을 때' 표시가 핵심",
    "7": "popleft = FIFO — 가장 오래된(가까운 층) 것부터",
    "8": "목표 도달 즉시 반환 — BFS라 이게 최단",
    "10": "방향 벡터 4개 — 상하좌우를 튜플로 순회",
    "12": "경계 검사 — 격자 밖 인덱스 방지 (0 <= x < n 패턴)",
    "13": "벽(1) 아님 + 미방문일 때만",
    "14": "★큐에 넣기 전에 seen 추가 — 꺼낼 때 추가하면 중복 삽입 폭발",
    "15": "이웃은 현재 거리 +1",
    "17": "큐 소진 = 모든 도달 가능 칸 탐색 완료, 목표 못 만남"
  },
  "resources": [
    {
      "name": "백준 2178 미로 탐색 (실버1)",
      "url": "https://www.acmicpc.net/problem/2178"
    },
    {
      "name": "HackerRank — BFS: Shortest Reach",
      "url": "https://www.hackerrank.com/challenges/bfsshortreach/problem"
    },
    {
      "name": "HackerRank — Connected Cells in a Grid",
      "url": "https://www.hackerrank.com/challenges/connected-cell-in-a-grid/problem"
    },
    {
      "name": "백준 1926 그림 (실버1)",
      "url": "https://www.acmicpc.net/problem/1926"
    }
  ],
  "func": "bfs",
  "tests": [
    {
      "args_repr": "([[0,0],[0,0]], (0,0), (1,1))",
      "expected": 2
    },
    {
      "args_repr": "([[0,1],[0,0]], (0,0), (1,1))",
      "expected": 2
    },
    {
      "args_repr": "([[0,1],[1,0]], (0,0), (1,1))",
      "expected": -1
    },
    {
      "args_repr": "([[0]], (0,0), (0,0))",
      "expected": 0
    },
    {
      "args_repr": "([[0,0,0],[1,1,0],[0,0,0]], (0,0), (2,0))",
      "expected": 6
    }
  ],
  "perf": {
    "gen": "def make_args():\n    n = 400\n    grid = [[0]*n for _ in range(n)]\n    return (grid, (0,0), (n-1,n-1))",
    "time_limit": 3.0
  },
  "diagram": {
    "caption": "BFS 파도 전파 — 같은 숫자 = 같은 거리 층. 목표(G)에 처음 닿는 층 = 최단거리",
    "fps": 1.2,
    "frames": [
      "S · · █ · · ·\n· · · █ · · ·\n· · · · · · G\n\n큐: [S]           시작점을 큐에",
      "S 1 · █ · · ·\n1 · · █ · · ·\n· · · · · · G\n\n큐: [1,1]         거리1 층 전부",
      "S 1 2 █ · · ·\n1 2 · █ · · ·\n2 · · · · · G\n\n큐: [2,2,2]       거리2 층 전부",
      "S 1 2 █ · · ·\n1 2 3 █ · · ·\n2 3 4 5 · · G\n\n큐: [3,3,4,5]     벽(█)은 돌아서",
      "S 1 2 █ 7 8 9\n1 2 3 █ 6 7 8\n2 3 4 5 6 7 G←8\n\n🎯 G 도달 = 8층   처음 닿은 순간이 최단!"
    ]
  },
  "statement": "문제 설명\nn×m 격자 지도가 주어집니다. 0은 지나갈 수 있는 칸, 1은 벽입니다. 시작 칸 start에서 목표 칸 goal까지 상하좌우로 한 칸씩 이동할 때, 필요한 최소 이동 횟수를 구하려 합니다.\n\ngrid, start(행, 열), goal(행, 열)이 주어질 때 최소 이동 횟수를 반환하고, 도달할 수 없으면 -1을 반환하도록 bfs 함수를 작성하세요. 시작 칸과 목표 칸이 같으면 0입니다.\n\n제한사항\n- 1 ≤ n, m ≤ 400\n- start와 goal은 항상 0인 칸입니다.\n\n입출력 예\ngrid = [[0,0],[0,0]], start = (0,0), goal = (1,1)  →  result = 2\ngrid = [[0,1],[0,0]], start = (0,0), goal = (1,1)  →  result = 2\n\n입출력 예 설명\n예제 #2: 오른쪽 칸이 벽이라 아래로 내려간 뒤 오른쪽으로 이동합니다(2번).",
  "statement_lang": "ko"
}